{"Timestamp":"2025-03-14T19:37:17.2329086-03:00","Level":"Information","MessageTemplate":"Now listening on: {address}","RenderedMessage":"Now listening on: \"http://localhost:5147\"","Properties":{"address":"http://localhost:5147","EventId":{"Id":14,"Name":"ListeningOnAddress"},"SourceContext":"Microsoft.Hosting.Lifetime"}}
{"Timestamp":"2025-03-14T19:37:17.2528770-03:00","Level":"Information","MessageTemplate":"Application started. Press Ctrl+C to shut down.","RenderedMessage":"Application started. Press Ctrl+C to shut down.","Properties":{"SourceContext":"Microsoft.Hosting.Lifetime"}}
{"Timestamp":"2025-03-14T19:37:17.2537605-03:00","Level":"Information","MessageTemplate":"Hosting environment: {EnvName}","RenderedMessage":"Hosting environment: \"Development\"","Properties":{"EnvName":"Development","SourceContext":"Microsoft.Hosting.Lifetime"}}
{"Timestamp":"2025-03-14T19:37:17.2544886-03:00","Level":"Information","MessageTemplate":"Content root path: {ContentRoot}","RenderedMessage":"Content root path: \"D:\\Github\\dotnet\\dotnet-observability-datadog\\src\\Companies.API\"","Properties":{"ContentRoot":"D:\\Github\\dotnet\\dotnet-observability-datadog\\src\\Companies.API","SourceContext":"Microsoft.Hosting.Lifetime"}}
{"Timestamp":"2025-03-14T19:37:28.0250546-03:00","Level":"Information","MessageTemplate":"Request starting {Protocol} {Method} {Scheme}://{Host}{PathBase}{Path}{QueryString} - {ContentType} {ContentLength}","RenderedMessage":"Request starting \"HTTP/1.1\" \"POST\" \"http\"://\"localhost:5147\"\"\"\"/companies\"\"\" - \"application/json\" 93","TraceId":"3786a6729d3897786097b77467751dc1","SpanId":"cfee179b3a2ba622","Properties":{"Protocol":"HTTP/1.1","Method":"POST","ContentType":"application/json","ContentLength":93,"Scheme":"http","Host":"localhost:5147","PathBase":"","Path":"/companies","QueryString":"","EventId":{"Id":1},"SourceContext":"Microsoft.AspNetCore.Hosting.Diagnostics","RequestId":"0HNB3936BJD66:00000001","RequestPath":"/companies","ConnectionId":"0HNB3936BJD66"}}
{"Timestamp":"2025-03-14T19:37:28.0822477-03:00","Level":"Warning","MessageTemplate":"Failed to determine the https port for redirect.","RenderedMessage":"Failed to determine the https port for redirect.","TraceId":"3786a6729d3897786097b77467751dc1","SpanId":"cfee179b3a2ba622","Properties":{"EventId":{"Id":3,"Name":"FailedToDeterminePort"},"SourceContext":"Microsoft.AspNetCore.HttpsPolicy.HttpsRedirectionMiddleware","RequestId":"0HNB3936BJD66:00000001","RequestPath":"/companies","ConnectionId":"0HNB3936BJD66"}}
{"Timestamp":"2025-03-14T19:37:28.0852997-03:00","Level":"Information","MessageTemplate":"Executing endpoint '{EndpointName}'","RenderedMessage":"Executing endpoint '\"HTTP: POST /companies => CreateCompany\"'","TraceId":"3786a6729d3897786097b77467751dc1","SpanId":"cfee179b3a2ba622","Properties":{"EndpointName":"HTTP: POST /companies => CreateCompany","EventId":{"Name":"ExecutingEndpoint"},"SourceContext":"Microsoft.AspNetCore.Routing.EndpointMiddleware","RequestId":"0HNB3936BJD66:00000001","RequestPath":"/companies","ConnectionId":"0HNB3936BJD66"}}
{"Timestamp":"2025-03-14T19:37:28.0965020-03:00","Level":"Information","MessageTemplate":"Creating company {@CreateCompany}","RenderedMessage":"Creating company CreateCompany { Name: \"Company Test\", Country: \"Brasil\", Email: \"company@email.com\" }","TraceId":"3786a6729d3897786097b77467751dc1","SpanId":"cfee179b3a2ba622","Properties":{"CreateCompany":{"Name":"Company Test","Country":"Brasil","Email":"company@email.com","_typeTag":"CreateCompany"},"SourceContext":"Program","RequestId":"0HNB3936BJD66:00000001","RequestPath":"/companies","ConnectionId":"0HNB3936BJD66"}}
{"Timestamp":"2025-03-14T19:37:28.1000227-03:00","Level":"Information","MessageTemplate":"Company created {@CompanyCreated}","RenderedMessage":"Company created CompanyCreated { Name: \"Company Test\", Country: \"Brasil\", Email: \"company@email.com\", Id: 0db6ecfb-f084-41c6-bdb5-7708e4c6aa13 }","TraceId":"3786a6729d3897786097b77467751dc1","SpanId":"cfee179b3a2ba622","Properties":{"CompanyCreated":{"Name":"Company Test","Country":"Brasil","Email":"company@email.com","Id":"0db6ecfb-f084-41c6-bdb5-7708e4c6aa13","_typeTag":"CompanyCreated"},"SourceContext":"Program","RequestId":"0HNB3936BJD66:00000001","RequestPath":"/companies","ConnectionId":"0HNB3936BJD66"}}
{"Timestamp":"2025-03-14T19:37:28.1074308-03:00","Level":"Information","MessageTemplate":"Setting HTTP status code {StatusCode}.","RenderedMessage":"Setting HTTP status code 201.","TraceId":"3786a6729d3897786097b77467751dc1","SpanId":"cfee179b3a2ba622","Properties":{"StatusCode":201,"EventId":{"Id":1,"Name":"WritingResultAsStatusCode"},"SourceContext":"Microsoft.AspNetCore.Http.Result.CreatedResult","RequestId":"0HNB3936BJD66:00000001","RequestPath":"/companies","ConnectionId":"0HNB3936BJD66"}}
{"Timestamp":"2025-03-14T19:37:28.1119879-03:00","Level":"Information","MessageTemplate":"Writing value of type '{Type}' as Json.","RenderedMessage":"Writing value of type '\"CompanyCreated\"' as Json.","TraceId":"3786a6729d3897786097b77467751dc1","SpanId":"cfee179b3a2ba622","Properties":{"Type":"CompanyCreated","EventId":{"Id":3,"Name":"WritingResultAsJson"},"SourceContext":"Microsoft.AspNetCore.Http.Result.CreatedResult","RequestId":"0HNB3936BJD66:00000001","RequestPath":"/companies","ConnectionId":"0HNB3936BJD66"}}
{"Timestamp":"2025-03-14T19:37:28.1189677-03:00","Level":"Information","MessageTemplate":"Executed endpoint '{EndpointName}'","RenderedMessage":"Executed endpoint '\"HTTP: POST /companies => CreateCompany\"'","TraceId":"3786a6729d3897786097b77467751dc1","SpanId":"cfee179b3a2ba622","Properties":{"EndpointName":"HTTP: POST /companies => CreateCompany","EventId":{"Id":1,"Name":"ExecutedEndpoint"},"SourceContext":"Microsoft.AspNetCore.Routing.EndpointMiddleware","RequestId":"0HNB3936BJD66:00000001","RequestPath":"/companies","ConnectionId":"0HNB3936BJD66"}}
{"Timestamp":"2025-03-14T19:37:28.1213347-03:00","Level":"Information","MessageTemplate":"Request finished {Protocol} {Method} {Scheme}://{Host}{PathBase}{Path}{QueryString} - {StatusCode} {ContentLength} {ContentType} {ElapsedMilliseconds}ms","RenderedMessage":"Request finished \"HTTP/1.1\" \"POST\" \"http\"://\"localhost:5147\"\"\"\"/companies\"\"\" - 201 null \"application/json; charset=utf-8\" 97.3207ms","TraceId":"3786a6729d3897786097b77467751dc1","SpanId":"cfee179b3a2ba622","Properties":{"ElapsedMilliseconds":97.3207,"StatusCode":201,"ContentType":"application/json; charset=utf-8","ContentLength":null,"Protocol":"HTTP/1.1","Method":"POST","Scheme":"http","Host":"localhost:5147","PathBase":"","Path":"/companies","QueryString":"","EventId":{"Id":2},"SourceContext":"Microsoft.AspNetCore.Hosting.Diagnostics","RequestId":"0HNB3936BJD66:00000001","RequestPath":"/companies","ConnectionId":"0HNB3936BJD66"}}
{"Timestamp":"2025-03-14T19:37:35.6417750-03:00","Level":"Information","MessageTemplate":"Request starting {Protocol} {Method} {Scheme}://{Host}{PathBase}{Path}{QueryString} - {ContentType} {ContentLength}","RenderedMessage":"Request starting \"HTTP/1.1\" \"POST\" \"http\"://\"localhost:5147\"\"\"\"/companies\"\"\" - \"application/json\" 93","TraceId":"a8f010ff748a2559859f1aa116aeb181","SpanId":"2e89845289cab059","Properties":{"Protocol":"HTTP/1.1","Method":"POST","ContentType":"application/json","ContentLength":93,"Scheme":"http","Host":"localhost:5147","PathBase":"","Path":"/companies","QueryString":"","EventId":{"Id":1},"SourceContext":"Microsoft.AspNetCore.Hosting.Diagnostics","RequestId":"0HNB3936BJD67:00000001","RequestPath":"/companies","ConnectionId":"0HNB3936BJD67"}}
{"Timestamp":"2025-03-14T19:37:35.6445081-03:00","Level":"Information","MessageTemplate":"Executing endpoint '{EndpointName}'","RenderedMessage":"Executing endpoint '\"HTTP: POST /companies => CreateCompany\"'","TraceId":"a8f010ff748a2559859f1aa116aeb181","SpanId":"2e89845289cab059","Properties":{"EndpointName":"HTTP: POST /companies => CreateCompany","EventId":{"Name":"ExecutingEndpoint"},"SourceContext":"Microsoft.AspNetCore.Routing.EndpointMiddleware","RequestId":"0HNB3936BJD67:00000001","RequestPath":"/companies","ConnectionId":"0HNB3936BJD67"}}
{"Timestamp":"2025-03-14T19:37:35.6460843-03:00","Level":"Information","MessageTemplate":"Creating company {@CreateCompany}","RenderedMessage":"Creating company CreateCompany { Name: \"Company Test\", Country: \"Brasil\", Email: \"company@email.com\" }","TraceId":"a8f010ff748a2559859f1aa116aeb181","SpanId":"2e89845289cab059","Properties":{"CreateCompany":{"Name":"Company Test","Country":"Brasil","Email":"company@email.com","_typeTag":"CreateCompany"},"SourceContext":"Program","RequestId":"0HNB3936BJD67:00000001","RequestPath":"/companies","ConnectionId":"0HNB3936BJD67"}}
{"Timestamp":"2025-03-14T19:37:35.6487985-03:00","Level":"Information","MessageTemplate":"Company created {@CompanyCreated}","RenderedMessage":"Company created CompanyCreated { Name: \"Company Test\", Country: \"Brasil\", Email: \"company@email.com\", Id: 5dcce6b3-6525-48db-9743-99ede1e8f623 }","TraceId":"a8f010ff748a2559859f1aa116aeb181","SpanId":"2e89845289cab059","Properties":{"CompanyCreated":{"Name":"Company Test","Country":"Brasil","Email":"company@email.com","Id":"5dcce6b3-6525-48db-9743-99ede1e8f623","_typeTag":"CompanyCreated"},"SourceContext":"Program","RequestId":"0HNB3936BJD67:00000001","RequestPath":"/companies","ConnectionId":"0HNB3936BJD67"}}
{"Timestamp":"2025-03-14T19:37:35.6520050-03:00","Level":"Information","MessageTemplate":"Setting HTTP status code {StatusCode}.","RenderedMessage":"Setting HTTP status code 201.","TraceId":"a8f010ff748a2559859f1aa116aeb181","SpanId":"2e89845289cab059","Properties":{"StatusCode":201,"EventId":{"Id":1,"Name":"WritingResultAsStatusCode"},"SourceContext":"Microsoft.AspNetCore.Http.Result.CreatedResult","RequestId":"0HNB3936BJD67:00000001","RequestPath":"/companies","ConnectionId":"0HNB3936BJD67"}}
{"Timestamp":"2025-03-14T19:37:35.6527941-03:00","Level":"Information","MessageTemplate":"Writing value of type '{Type}' as Json.","RenderedMessage":"Writing value of type '\"CompanyCreated\"' as Json.","TraceId":"a8f010ff748a2559859f1aa116aeb181","SpanId":"2e89845289cab059","Properties":{"Type":"CompanyCreated","EventId":{"Id":3,"Name":"WritingResultAsJson"},"SourceContext":"Microsoft.AspNetCore.Http.Result.CreatedResult","RequestId":"0HNB3936BJD67:00000001","RequestPath":"/companies","ConnectionId":"0HNB3936BJD67"}}
{"Timestamp":"2025-03-14T19:37:35.6539422-03:00","Level":"Information","MessageTemplate":"Executed endpoint '{EndpointName}'","RenderedMessage":"Executed endpoint '\"HTTP: POST /companies => CreateCompany\"'","TraceId":"a8f010ff748a2559859f1aa116aeb181","SpanId":"2e89845289cab059","Properties":{"EndpointName":"HTTP: POST /companies => CreateCompany","EventId":{"Id":1,"Name":"ExecutedEndpoint"},"SourceContext":"Microsoft.AspNetCore.Routing.EndpointMiddleware","RequestId":"0HNB3936BJD67:00000001","RequestPath":"/companies","ConnectionId":"0HNB3936BJD67"}}
{"Timestamp":"2025-03-14T19:37:35.6548876-03:00","Level":"Information","MessageTemplate":"Request finished {Protocol} {Method} {Scheme}://{Host}{PathBase}{Path}{QueryString} - {StatusCode} {ContentLength} {ContentType} {ElapsedMilliseconds}ms","RenderedMessage":"Request finished \"HTTP/1.1\" \"POST\" \"http\"://\"localhost:5147\"\"\"\"/companies\"\"\" - 201 null \"application/json; charset=utf-8\" 13.3197ms","TraceId":"a8f010ff748a2559859f1aa116aeb181","SpanId":"2e89845289cab059","Properties":{"ElapsedMilliseconds":13.3197,"StatusCode":201,"ContentType":"application/json; charset=utf-8","ContentLength":null,"Protocol":"HTTP/1.1","Method":"POST","Scheme":"http","Host":"localhost:5147","PathBase":"","Path":"/companies","QueryString":"","EventId":{"Id":2},"SourceContext":"Microsoft.AspNetCore.Hosting.Diagnostics","RequestId":"0HNB3936BJD67:00000001","RequestPath":"/companies","ConnectionId":"0HNB3936BJD67"}}
{"Timestamp":"2025-03-14T19:37:38.2783960-03:00","Level":"Information","MessageTemplate":"Request starting {Protocol} {Method} {Scheme}://{Host}{PathBase}{Path}{QueryString} - {ContentType} {ContentLength}","RenderedMessage":"Request starting \"HTTP/1.1\" \"POST\" \"http\"://\"localhost:5147\"\"\"\"/companies\"\"\" - \"application/json\" 93","TraceId":"af38fbf6f9978311039e1241d6fd5f92","SpanId":"c71535ded9b78316","Properties":{"Protocol":"HTTP/1.1","Method":"POST","ContentType":"application/json","ContentLength":93,"Scheme":"http","Host":"localhost:5147","PathBase":"","Path":"/companies","QueryString":"","EventId":{"Id":1},"SourceContext":"Microsoft.AspNetCore.Hosting.Diagnostics","RequestId":"0HNB3936BJD68:00000001","RequestPath":"/companies","ConnectionId":"0HNB3936BJD68"}}
{"Timestamp":"2025-03-14T19:37:38.2802948-03:00","Level":"Information","MessageTemplate":"Executing endpoint '{EndpointName}'","RenderedMessage":"Executing endpoint '\"HTTP: POST /companies => CreateCompany\"'","TraceId":"af38fbf6f9978311039e1241d6fd5f92","SpanId":"c71535ded9b78316","Properties":{"EndpointName":"HTTP: POST /companies => CreateCompany","EventId":{"Name":"ExecutingEndpoint"},"SourceContext":"Microsoft.AspNetCore.Routing.EndpointMiddleware","RequestId":"0HNB3936BJD68:00000001","RequestPath":"/companies","ConnectionId":"0HNB3936BJD68"}}
{"Timestamp":"2025-03-14T19:37:38.2814442-03:00","Level":"Information","MessageTemplate":"Creating company {@CreateCompany}","RenderedMessage":"Creating company CreateCompany { Name: \"Company Test\", Country: \"Brasil\", Email: \"company@email.com\" }","TraceId":"af38fbf6f9978311039e1241d6fd5f92","SpanId":"c71535ded9b78316","Properties":{"CreateCompany":{"Name":"Company Test","Country":"Brasil","Email":"company@email.com","_typeTag":"CreateCompany"},"SourceContext":"Program","RequestId":"0HNB3936BJD68:00000001","RequestPath":"/companies","ConnectionId":"0HNB3936BJD68"}}
{"Timestamp":"2025-03-14T19:37:38.2843102-03:00","Level":"Information","MessageTemplate":"Company created {@CompanyCreated}","RenderedMessage":"Company created CompanyCreated { Name: \"Company Test\", Country: \"Brasil\", Email: \"company@email.com\", Id: d0e2043f-34a0-44e5-bd65-e7d3a230fafe }","TraceId":"af38fbf6f9978311039e1241d6fd5f92","SpanId":"c71535ded9b78316","Properties":{"CompanyCreated":{"Name":"Company Test","Country":"Brasil","Email":"company@email.com","Id":"d0e2043f-34a0-44e5-bd65-e7d3a230fafe","_typeTag":"CompanyCreated"},"SourceContext":"Program","RequestId":"0HNB3936BJD68:00000001","RequestPath":"/companies","ConnectionId":"0HNB3936BJD68"}}
{"Timestamp":"2025-03-14T19:37:38.2869888-03:00","Level":"Information","MessageTemplate":"Setting HTTP status code {StatusCode}.","RenderedMessage":"Setting HTTP status code 201.","TraceId":"af38fbf6f9978311039e1241d6fd5f92","SpanId":"c71535ded9b78316","Properties":{"StatusCode":201,"EventId":{"Id":1,"Name":"WritingResultAsStatusCode"},"SourceContext":"Microsoft.AspNetCore.Http.Result.CreatedResult","RequestId":"0HNB3936BJD68:00000001","RequestPath":"/companies","ConnectionId":"0HNB3936BJD68"}}
{"Timestamp":"2025-03-14T19:37:38.2877688-03:00","Level":"Information","MessageTemplate":"Writing value of type '{Type}' as Json.","RenderedMessage":"Writing value of type '\"CompanyCreated\"' as Json.","TraceId":"af38fbf6f9978311039e1241d6fd5f92","SpanId":"c71535ded9b78316","Properties":{"Type":"CompanyCreated","EventId":{"Id":3,"Name":"WritingResultAsJson"},"SourceContext":"Microsoft.AspNetCore.Http.Result.CreatedResult","RequestId":"0HNB3936BJD68:00000001","RequestPath":"/companies","ConnectionId":"0HNB3936BJD68"}}
{"Timestamp":"2025-03-14T19:37:38.2886488-03:00","Level":"Information","MessageTemplate":"Executed endpoint '{EndpointName}'","RenderedMessage":"Executed endpoint '\"HTTP: POST /companies => CreateCompany\"'","TraceId":"af38fbf6f9978311039e1241d6fd5f92","SpanId":"c71535ded9b78316","Properties":{"EndpointName":"HTTP: POST /companies => CreateCompany","EventId":{"Id":1,"Name":"ExecutedEndpoint"},"SourceContext":"Microsoft.AspNetCore.Routing.EndpointMiddleware","RequestId":"0HNB3936BJD68:00000001","RequestPath":"/companies","ConnectionId":"0HNB3936BJD68"}}
{"Timestamp":"2025-03-14T19:37:38.2893910-03:00","Level":"Information","MessageTemplate":"Request finished {Protocol} {Method} {Scheme}://{Host}{PathBase}{Path}{QueryString} - {StatusCode} {ContentLength} {ContentType} {ElapsedMilliseconds}ms","RenderedMessage":"Request finished \"HTTP/1.1\" \"POST\" \"http\"://\"localhost:5147\"\"\"\"/companies\"\"\" - 201 null \"application/json; charset=utf-8\" 10.9912ms","TraceId":"af38fbf6f9978311039e1241d6fd5f92","SpanId":"c71535ded9b78316","Properties":{"ElapsedMilliseconds":10.9912,"StatusCode":201,"ContentType":"application/json; charset=utf-8","ContentLength":null,"Protocol":"HTTP/1.1","Method":"POST","Scheme":"http","Host":"localhost:5147","PathBase":"","Path":"/companies","QueryString":"","EventId":{"Id":2},"SourceContext":"Microsoft.AspNetCore.Hosting.Diagnostics","RequestId":"0HNB3936BJD68:00000001","RequestPath":"/companies","ConnectionId":"0HNB3936BJD68"}}
{"Timestamp":"2025-03-14T19:37:41.7384883-03:00","Level":"Information","MessageTemplate":"Request starting {Protocol} {Method} {Scheme}://{Host}{PathBase}{Path}{QueryString} - {ContentType} {ContentLength}","RenderedMessage":"Request starting \"HTTP/1.1\" \"POST\" \"http\"://\"localhost:5147\"\"\"\"/companies\"\"\" - \"application/json\" 93","TraceId":"61458fcb00e858473ffb907d69ac172e","SpanId":"aefcd2b66e8a4fb7","Properties":{"Protocol":"HTTP/1.1","Method":"POST","ContentType":"application/json","ContentLength":93,"Scheme":"http","Host":"localhost:5147","PathBase":"","Path":"/companies","QueryString":"","EventId":{"Id":1},"SourceContext":"Microsoft.AspNetCore.Hosting.Diagnostics","RequestId":"0HNB3936BJD69:00000001","RequestPath":"/companies","ConnectionId":"0HNB3936BJD69"}}
{"Timestamp":"2025-03-14T19:37:41.7408936-03:00","Level":"Information","MessageTemplate":"Executing endpoint '{EndpointName}'","RenderedMessage":"Executing endpoint '\"HTTP: POST /companies => CreateCompany\"'","TraceId":"61458fcb00e858473ffb907d69ac172e","SpanId":"aefcd2b66e8a4fb7","Properties":{"EndpointName":"HTTP: POST /companies => CreateCompany","EventId":{"Name":"ExecutingEndpoint"},"SourceContext":"Microsoft.AspNetCore.Routing.EndpointMiddleware","RequestId":"0HNB3936BJD69:00000001","RequestPath":"/companies","ConnectionId":"0HNB3936BJD69"}}
{"Timestamp":"2025-03-14T19:37:41.7420856-03:00","Level":"Information","MessageTemplate":"Creating company {@CreateCompany}","RenderedMessage":"Creating company CreateCompany { Name: \"Company Test\", Country: \"Brasil\", Email: \"company@email.com\" }","TraceId":"61458fcb00e858473ffb907d69ac172e","SpanId":"aefcd2b66e8a4fb7","Properties":{"CreateCompany":{"Name":"Company Test","Country":"Brasil","Email":"company@email.com","_typeTag":"CreateCompany"},"SourceContext":"Program","RequestId":"0HNB3936BJD69:00000001","RequestPath":"/companies","ConnectionId":"0HNB3936BJD69"}}
{"Timestamp":"2025-03-14T19:37:41.7443457-03:00","Level":"Information","MessageTemplate":"Company created {@CompanyCreated}","RenderedMessage":"Company created CompanyCreated { Name: \"Company Test\", Country: \"Brasil\", Email: \"company@email.com\", Id: 42f0dbc8-f19a-4078-b078-bfdc16094be4 }","TraceId":"61458fcb00e858473ffb907d69ac172e","SpanId":"aefcd2b66e8a4fb7","Properties":{"CompanyCreated":{"Name":"Company Test","Country":"Brasil","Email":"company@email.com","Id":"42f0dbc8-f19a-4078-b078-bfdc16094be4","_typeTag":"CompanyCreated"},"SourceContext":"Program","RequestId":"0HNB3936BJD69:00000001","RequestPath":"/companies","ConnectionId":"0HNB3936BJD69"}}
{"Timestamp":"2025-03-14T19:37:41.7469194-03:00","Level":"Information","MessageTemplate":"Setting HTTP status code {StatusCode}.","RenderedMessage":"Setting HTTP status code 201.","TraceId":"61458fcb00e858473ffb907d69ac172e","SpanId":"aefcd2b66e8a4fb7","Properties":{"StatusCode":201,"EventId":{"Id":1,"Name":"WritingResultAsStatusCode"},"SourceContext":"Microsoft.AspNetCore.Http.Result.CreatedResult","RequestId":"0HNB3936BJD69:00000001","RequestPath":"/companies","ConnectionId":"0HNB3936BJD69"}}
{"Timestamp":"2025-03-14T19:37:41.7477814-03:00","Level":"Information","MessageTemplate":"Writing value of type '{Type}' as Json.","RenderedMessage":"Writing value of type '\"CompanyCreated\"' as Json.","TraceId":"61458fcb00e858473ffb907d69ac172e","SpanId":"aefcd2b66e8a4fb7","Properties":{"Type":"CompanyCreated","EventId":{"Id":3,"Name":"WritingResultAsJson"},"SourceContext":"Microsoft.AspNetCore.Http.Result.CreatedResult","RequestId":"0HNB3936BJD69:00000001","RequestPath":"/companies","ConnectionId":"0HNB3936BJD69"}}
{"Timestamp":"2025-03-14T19:37:41.7485962-03:00","Level":"Information","MessageTemplate":"Executed endpoint '{EndpointName}'","RenderedMessage":"Executed endpoint '\"HTTP: POST /companies => CreateCompany\"'","TraceId":"61458fcb00e858473ffb907d69ac172e","SpanId":"aefcd2b66e8a4fb7","Properties":{"EndpointName":"HTTP: POST /companies => CreateCompany","EventId":{"Id":1,"Name":"ExecutedEndpoint"},"SourceContext":"Microsoft.AspNetCore.Routing.EndpointMiddleware","RequestId":"0HNB3936BJD69:00000001","RequestPath":"/companies","ConnectionId":"0HNB3936BJD69"}}
{"Timestamp":"2025-03-14T19:37:41.7493843-03:00","Level":"Information","MessageTemplate":"Request finished {Protocol} {Method} {Scheme}://{Host}{PathBase}{Path}{QueryString} - {StatusCode} {ContentLength} {ContentType} {ElapsedMilliseconds}ms","RenderedMessage":"Request finished \"HTTP/1.1\" \"POST\" \"http\"://\"localhost:5147\"\"\"\"/companies\"\"\" - 201 null \"application/json; charset=utf-8\" 10.9048ms","TraceId":"61458fcb00e858473ffb907d69ac172e","SpanId":"aefcd2b66e8a4fb7","Properties":{"ElapsedMilliseconds":10.9048,"StatusCode":201,"ContentType":"application/json; charset=utf-8","ContentLength":null,"Protocol":"HTTP/1.1","Method":"POST","Scheme":"http","Host":"localhost:5147","PathBase":"","Path":"/companies","QueryString":"","EventId":{"Id":2},"SourceContext":"Microsoft.AspNetCore.Hosting.Diagnostics","RequestId":"0HNB3936BJD69:00000001","RequestPath":"/companies","ConnectionId":"0HNB3936BJD69"}}
